cssl/__init__.py
cssl-0.0.0.2.dist-info/LICENSE
cssl-0.0.0.2.dist-info/METADATA
cssl-0.0.0.2.dist-info/WHEEL
cssl-0.0.0.2.dist-info/top_level.txt
cssl-0.0.0.2.dist-info/RECORD
