Metadata-Version: 2.1
Name: cssl
Version: 0.0.0.2
Summary: package for css experiments of sem6
Home-page: https://github.com/RishabhBhatnagar
Author: Rishabh Bhatnagar
Author-email: bhatnagarrishabh4@gmail.com
License: UNKNOWN
Platform: UNKNOWN
Classifier: Programming Language :: Python :: 3
Classifier: License :: OSI Approved :: MIT License
Classifier: Operating System :: OS Independent
